AUTHORS
Changelog
LICENSE
MANIFEST.in
README
README.rst
THANKS
TODO
setup.cfg
setup.py
contrib/mailman/archive_and_index.py
pyes/__init__.py
pyes/aggs.py
pyes/connection.py
pyes/connection_http.py
pyes/convert_errors.py
pyes/decorators.py
pyes/djangoutils.py
pyes/es.py
pyes/exceptions.py
pyes/facets.py
pyes/fakettypes.py
pyes/filters.py
pyes/helpers.py
pyes/highlight.py
pyes/managers.py
pyes/mappings.py
pyes/models.py
pyes/query.py
pyes/queryset.py
pyes/rivers.py
pyes/scriptfields.py
pyes/sort.py
pyes/tests.py
pyes.egg-info/PKG-INFO
pyes.egg-info/SOURCES.txt
pyes.egg-info/dependency_links.txt
pyes.egg-info/entry_points.txt
pyes.egg-info/not-zip-safe
pyes.egg-info/requires.txt
pyes.egg-info/top_level.txt
pyes/contrib/__init__.py
pyes/contrib/mappings.py
pyes/orm/__init__.py
pyes/orm/exceptions.py
pyes/orm/queryset.py
pyes/pyesthrift/Rest.py
pyes/pyesthrift/__init__.py
pyes/pyesthrift/constants.py
pyes/pyesthrift/simple_test.py
pyes/pyesthrift/ttypes.py
pyes/utils/__init__.py
pyes/utils/compat.py
pyes/utils/encoding.py
pyes/utils/five.py
pyes/utils/imports.py