Metadata-Version: 1.1
Name: pyes
Version: 0.99.5
Summary: Python Elastic Search driver
Home-page: http://github.com/aparo/pyes/
Author: Alberto Paro
Author-email: alberto.paro@gmail.com
License: BSD
Platform: any
Classifier: Development Status :: 2 - Pre-Alpha
Classifier: Intended Audience :: Developers
Classifier: License :: OSI Approved :: BSD License
Classifier: Operating System :: OS Independent
Classifier: Programming Language :: Python
Classifier: Topic :: Internet :: WWW/HTTP :: Indexing/Search
